picameleon/__init__.py
picameleon/main.py
picameleon/client/__init__.py
picameleon/client/client.py
picameleon/mode_executor/__init__.py
picameleon/mode_executor/mode_executor.py
picameleon/modes/__init__.py
picameleon/modes/base.py
picameleon/modes/motion_detection.py
picameleon/modes/network_serving.py
picameleon/modes/network_streaming.py
picameleon/modes/network_trigger.py
picameleon/modes/photo_motion_detection.py
picameleon/outputs/__init__.py
picameleon/outputs/client_socket_wrap.py
picameleon/outputs/motion_detector.py
picameleon/outputs/motion_output_holder.py
picameleon/outputs/output_holder.py
picameleon/outputs/server_socket_wrap.py
picameleon/streamers/__init__.py
picameleon/streamers/base.py
picameleon/streamers/split_frame.py
picameleon/streamers/streamer.py
picameleon/trigger_responses/__init__.py
picameleon/trigger_responses/base.py
picameleon/trigger_responses/dummy.py
picameleon/trigger_responses/http.py
picameleon/trigger_responses/record_to_file.py
picameleon/trigger_responses/snapshot.py
picameleon/trigger_responses/trigger_response_store.py
picameleon/utils/__init__.py
picameleon/utils/consts.py
picameleon/utils/single_picamera.py
picameleon-0.0.2.dist-info/LICENSE
picameleon-0.0.2.dist-info/METADATA
picameleon-0.0.2.dist-info/WHEEL
picameleon-0.0.2.dist-info/top_level.txt
picameleon-0.0.2.dist-info/RECORD
