Metadata-Version: 2.1
Name: picameleon
Version: 0.0.2
Summary: A python client or picameleon
Home-page: https://github.com/Esser50K/PiCameleon
Author: André Esser
Author-email: bepandre@hotmail.com
License: LGPLv3
Download-URL: https://github.com/Esser50K/PiCameleon/archive/refs/tags/picameleon-client-v0.0.2.tar.gz
Keywords: picamera,service,raspberrypi
Platform: ALL
Classifier: Development Status :: 3 - Alpha
Classifier: Intended Audience :: Developers
Classifier: Topic :: Software Development :: Build Tools
Classifier: License :: OSI Approved :: GNU General Public License v3 (GPLv3)
Classifier: Programming Language :: Python :: 3
Classifier: Programming Language :: Python :: 3.4
Classifier: Programming Language :: Python :: 3.5
Classifier: Programming Language :: Python :: 3.6
Classifier: Programming Language :: Python :: 3.7
Classifier: Programming Language :: Python :: 3.8
Classifier: Programming Language :: Python :: 3.9
Classifier: Programming Language :: Python :: 3.10
License-File: LICENSE
